{
  "parent": "minecraft:recipes/root",
  "criteria": {
    "has_item_replicator_tier5": {
      "conditions": {
        "items": [
          {
            "items": "resource_replicator:item_replicator_tier5"
          }
        ]
      },
      "trigger": "minecraft:inventory_changed"
    },
    "has_the_recipe": {
      "conditions": {
        "recipe": "resource_replicator:item_replicator_tier5"
      },
      "trigger": "minecraft:recipe_unlocked"
    }
  },
  "requirements": [
    [
      "has_the_recipe",
      "has_item_replicator_tier5"
    ]
  ],
  "rewards": {
    "recipes": [
      "resource_replicator:item_replicator_tier5"
    ]
  }
}